ssh_pam_manager/__init__.py
ssh_pam_manager/cli_interface.py
ssh_pam_manager/config_validator.py
ssh_pam_manager/main.py
ssh_pam_manager/pam_manager.py
ssh_pam_manager/pam_parser.py
ssh_pam_manager-1.0.0.dist-info/licenses/LICENSE
ssh_pam_manager-1.0.0.dist-info/METADATA
ssh_pam_manager-1.0.0.dist-info/WHEEL
ssh_pam_manager-1.0.0.dist-info/entry_points.txt
ssh_pam_manager-1.0.0.dist-info/top_level.txt
ssh_pam_manager-1.0.0.dist-info/RECORD
