Metadata-Version: 2.4
Name: ssh-pam-manager
Version: 1.0.0
Summary: A Python tool for managing SSH PAM configurations on Linux systems
Author-email: SSH PAM Manager Team <liumou.site@qq.com>
License: MIT
Project-URL: Homepage, https://gitee.com/liumou_site/ssh-pam-management
Project-URL: Documentation, https://gitee.com/liumou_site/ssh-pam-management#readme
Project-URL: Repository, https://gitee.com/liumou_site/ssh-pam-management
Project-URL: Issues, https://gitee.com/liumou_site/ssh-pam-management/issues
Keywords: ssh,pam,linux,authentication,security
Classifier: Development Status :: 4 - Beta
Classifier: Intended Audience :: System Administrators
Classifier: License :: OSI Approved :: MIT License
Classifier: Operating System :: POSIX :: Linux
Classifier: Programming Language :: Python :: 3
Classifier: Programming Language :: Python :: 3.7
Classifier: Programming Language :: Python :: 3.8
Classifier: Programming Language :: Python :: 3.9
Classifier: Programming Language :: Python :: 3.10
Classifier: Programming Language :: Python :: 3.11
Classifier: Programming Language :: Python :: 3.12
Classifier: Topic :: System :: Systems Administration
Classifier: Topic :: Security
Requires-Python: >=3.7
License-File: LICENSE
Dynamic: license-file
